Text-Adventure-Engine/__init__.py
Text-Adventure-Engine/character.py
Text-Adventure-Engine/error.py
Text-Adventure-Engine/interaction.py
Text-Adventure-Engine/item.py
Text-Adventure-Engine/text.py
TextEngine/__init__.py
TextEngine/character.py
TextEngine/error.py
TextEngine/interaction.py
TextEngine/item.py
TextEngine/text.py
tae/__init__.py
tae/character.py
tae/error.py
tae/interaction.py
tae/item.py
tae/text.py
TAE-1.0.1.dist-info/LICENSE
TAE-1.0.1.dist-info/METADATA
TAE-1.0.1.dist-info/WHEEL
TAE-1.0.1.dist-info/top_level.txt
TAE-1.0.1.dist-info/RECORD
