Metadata-Version: 2.1
Name: TAE
Version: 1.0.1
Summary: A Text Engine for Text Stories
Home-page: https://github.com/LapisPhoenix/Text-Engine
Author: Lapis Pheonix
Project-URL: Bug Tracker, https://github.com/LapisPhoenix/Text-Engine/issues
Classifier: Programming Language :: Python :: 3
Classifier: License :: OSI Approved :: Apache Software License
Classifier: Operating System :: OS Independent
Requires-Python: >=3.6
License-File: LICENSE
